__init__.py
pygame_layout.py
pygame_ui.py
pygame_layout-1.0.0.dist-info/LICENSE
pygame_layout-1.0.0.dist-info/METADATA
pygame_layout-1.0.0.dist-info/WHEEL
pygame_layout-1.0.0.dist-info/top_level.txt
pygame_layout-1.0.0.dist-info/RECORD
